brutils/__init__.py
brutils/cep.py
brutils/cnpj.py
brutils/cpf.py
brutils/currency.py
brutils/data/cities_code.json
brutils/data/enums/__init__.py
brutils/data/enums/better_enum.py
brutils/data/enums/months.py
brutils/data/enums/uf.py
brutils/data/legal_process_ids.json
brutils/date_utils.py
brutils/email.py
brutils/exceptions/__init__.py
brutils/exceptions/cep.py
brutils/ibge/__init__.py
brutils/ibge/municipality.py
brutils/ibge/uf.py
brutils/legal_process.py
brutils/license_plate.py
brutils/phone.py
brutils/pis.py
brutils/types/__init__.py
brutils/types/address.py
brutils/voter_id.py
brutils-2.3.0.dist-info/METADATA
brutils-2.3.0.dist-info/WHEEL
brutils-2.3.0.dist-info/licenses/LICENSE
brutils-2.3.0.dist-info/RECORD
