Metadata-Version: 2.4
Name: brutils
Version: 2.3.0
Summary: Utils library for specific Brazilian businesses
License: MIT
License-File: LICENSE
Keywords: cpf,cnpj,cep,document,validation,brazil,brazilian
Author: The Brazilian Utils Organization
Requires-Python: >=3.10,<4.0
Classifier: Development Status :: 5 - Production/Stable
Classifier: License :: OSI Approved :: MIT License
Classifier: Natural Language :: English
Classifier: Natural Language :: Portuguese
Classifier: Natural Language :: Portuguese (Brazilian)
Classifier: Programming Language :: Python
Classifier: Programming Language :: Python :: 3
Classifier: Programming Language :: Python :: 3.10
Classifier: Programming Language :: Python :: 3.11
Classifier: Programming Language :: Python :: 3.12
Classifier: Programming Language :: Python :: 3.13
Classifier: Programming Language :: Python :: 3.14
Classifier: Programming Language :: Python :: 3 :: Only
Classifier: Topic :: Office/Business
Classifier: Topic :: Software Development :: Internationalization
Classifier: Topic :: Software Development :: Libraries :: Python Modules
Requires-Dist: coverage (>=7.2.7,<8.0.0)
Requires-Dist: holidays (>=0.58,<0.59)
Requires-Dist: num2words (==0.5.14)
Project-URL: Repository, https://github.com/brazilian-utils/brutils
